{
  "words": [
    {
      "word": "Drop",
      "start": 0.0,
      "end": 0.354
    },
    {
      "word": "your",
      "start": 0.354,
      "end": 0.707
    },
    {
      "word": "take:",
      "start": 0.707,
      "end": 1.061
    },
    {
      "word": "Who's",
      "start": 1.061,
      "end": 1.415
    },
    {
      "word": "your",
      "start": 1.415,
      "end": 1.768
    },
    {
      "word": "top",
      "start": 1.768,
      "end": 2.122
    },
    {
      "word": "3",
      "start": 2.122,
      "end": 2.475
    },
    {
      "word": "favorite",
      "start": 2.475,
      "end": 2.829
    },
    {
      "word": "characters",
      "start": 2.829,
      "end": 3.183
    },
    {
      "word": "from",
      "start": 3.183,
      "end": 3.536
    },
    {
      "word": "Bleach?",
      "start": 3.536,
      "end": 3.89
    }
  ]
}